algorithms/__init__.py
algorithms/auction.py
algorithms/bankruptcy.py
gametheory-0.2.1.dist-info/licenses/LICENSE
utils/__init__.py
gametheory-0.2.1.dist-info/METADATA
gametheory-0.2.1.dist-info/WHEEL
gametheory-0.2.1.dist-info/top_level.txt
gametheory-0.2.1.dist-info/RECORD
