Metadata-Version: 2.4
Name: gameTheory
Version: 0.2.1
Summary: A library for game theory algorithms in Python
Author-email: Ali Faraji <ali@faraji.info>
License:                     GNU GENERAL PUBLIC LICENSE
Project-URL: Homepage, https://github.com/alifa98/GameKit/
Project-URL: Documentation, https://github.com/alifa98/GameKit/wiki
Project-URL: Source, https://github.com/alifa98/GameKit/
Classifier: Programming Language :: Python :: 3
Classifier: License :: OSI Approved :: GNU General Public License v3 (GPLv3)
Classifier: Operating System :: OS Independent
Requires-Python: >=3.9
License-File: LICENSE
Dynamic: license-file
